suppliers/__init__.py
suppliers/apps/__init__.py
suppliers/apps/category_app.py
suppliers/apps/supplier_list.py
suppliers/fixtures/initial_data.yaml
suppliers/migrations/0001_initial.py
suppliers/migrations/__init__.py
suppliers/models/__init__.py
suppliers/models/category.py
suppliers/models/history.py
suppliers/models/supplier.py
core_suppliers-0.2.dist-info/METADATA
core_suppliers-0.2.dist-info/WHEEL
core_suppliers-0.2.dist-info/top_level.txt
core_suppliers-0.2.dist-info/RECORD
