Metadata-Version: 2.1
Name: core-suppliers
Version: 0.2
Summary: Research CORE ERM - suppliers module
Home-page: https://github.com/research-core/core-suppliers
Author: Ricardo Ribeiro, Hugo Cachitas
Author-email: ricardojvr@gmail.com, hugo.cachitas@research.fchampalimaud.org
License: MIT
Platform: UNKNOWN
